IBB_Helper/__init__.py
IBB_Helper/animate.py
IBB_Helper/combine_plots.py
IBB_Helper/display.py
IBB_Helper/display_eigen.py
IBB_Helper/display_matrix.py
IBB_Helper/extend_plot.py
IBB_Helper/minimize.py
IBB_Helper/num_int.py
IBB_Helper/plot_2d.py
IBB_Helper/plot_3d.py
IBB_Helper/plot_param_grid.py
IBB_Helper/symbolic_BSpline.py
ibb_helper-0.4.7.dist-info/licenses/LICENSE
ibb_helper-0.4.7.dist-info/METADATA
ibb_helper-0.4.7.dist-info/WHEEL
ibb_helper-0.4.7.dist-info/top_level.txt
ibb_helper-0.4.7.dist-info/RECORD
