Metadata-Version: 2.4
Name: IBB_Helper
Version: 0.4.7
Summary: Helper functions for symbolic math, matrix visualization, and plotting
Author-email: "University of Stuttgart, Institute for Structural Mechanics (IBB)" <mvs@ibb.uni-stuttgart.de>
License-Expression: BSD-3-Clause
Project-URL: repository, https://www.ibb.uni-stuttgart.de/en/
Classifier: Programming Language :: Python :: 3
Classifier: Operating System :: OS Independent
License-File: LICENSE
Requires-Dist: numpy>=1.19
Requires-Dist: sympy>=1.8
Requires-Dist: matplotlib>=3.3
Requires-Dist: plotly>=5.0
Requires-Dist: ipython>=7.0
Dynamic: license-file
